shell_lite/__init__.py
shell_lite/ast_nodes.py
shell_lite/cli.py
shell_lite/compiler.py
shell_lite/interpreter.py
shell_lite/js_compiler.py
shell_lite/lexer.py
shell_lite/main.py
shell_lite/parser.py
shell_lite/parser_gbp.py
shell_lite/runtime.py
shell_lite-0.5.3.2.dist-info/LICENSE
shell_lite-0.5.3.2.dist-info/METADATA
shell_lite-0.5.3.2.dist-info/WHEEL
shell_lite-0.5.3.2.dist-info/entry_points.txt
shell_lite-0.5.3.2.dist-info/top_level.txt
shell_lite-0.5.3.2.dist-info/RECORD
