Metadata-Version: 2.1
Name: shell-lite
Version: 0.5.3.2
Summary: A lightweight, English-like scripting language.
Home-page: https://github.com/Shrey-N/ShellDesk
Author: Shrey Naithani
Author-email: Shrey Naithani <contact@shelllite.tech>
License: MIT
Classifier: Programming Language :: Python :: 3
Classifier: Operating System :: OS Independent
Requires-Python: >=3.8
License-File: LICENSE
Requires-Dist: prompt-toolkit>=3.0.0
